tetra/__init__.py
tetra/apps.py
tetra/build.py
tetra/checks.py
tetra/component_register.py
tetra/conf.py
tetra/constants.py
tetra/consumers.py
tetra/default_settings.py
tetra/dispatcher.py
tetra/exceptions.py
tetra/helpers.py
tetra/library.py
tetra/middleware.py
tetra/router.py
tetra/routing.py
tetra/state.py
tetra/templates.py
tetra/types.py
tetra/urls.py
tetra/utils.py
tetra/views.py
tetra/components/__init__.py
tetra/components/base.py
tetra/components/callbacks.py
tetra/components/reactive.py
tetra/components/subscription.py
tetra/js/tetra.core.js
tetra/js/tetra.js
tetra/loaders/__init__.py
tetra/loaders/components_directories.py
tetra/management/__init__.py
tetra/management/commands/__init__.py
tetra/management/commands/cleanup_temp_uploads.py
tetra/management/commands/makemessages.py
tetra/management/commands/runserver.py
tetra/management/commands/tetrabuild.py
tetra/static/tetra/css/tetra.css
tetra/static/tetra/js/alpinejs.cdn.js
tetra/static/tetra/js/alpinejs.cdn.min.js
tetra/static/tetra/js/alpinejs.morph.cdn.js
tetra/static/tetra/js/alpinejs.morph.cdn.min.js
tetra/static/tetra/js/tetra.js
tetra/static/tetra/js/tetra.js.map
tetra/static/tetra/js/tetra.min.js
tetra/static/tetra/js/tetra.min.js.map
tetra/static/tetra/tetra/default/tetra_default-AQ5647WS.js
tetra/static/tetra/tetra/default/tetra_default-AQ5647WS.js.map
tetra/static/tetra/tetra/default/tetra_default-WY5FVYVP.css
tetra/static/tetra/tetra/default/tetra_default-WY5FVYVP.css.map
tetra/static/tetra/tetra/default/tetra_default.css.filename
tetra/static/tetra/tetra/default/tetra_default.js.filename
tetra/static/tetra/tetra/test_router/tetra_test_router-6ID267HD.js
tetra/static/tetra/tetra/test_router/tetra_test_router-6ID267HD.js.map
tetra/static/tetra/tetra/test_router/tetra_test_router-XTQ52BTR.css
tetra/static/tetra/tetra/test_router/tetra_test_router-XTQ52BTR.css.map
tetra/static/tetra/tetra/test_router/tetra_test_router.css.filename
tetra-0.8.1.dist-info/licenses/LICENSE
tetra-0.8.1.dist-info/METADATA
tetra-0.8.1.dist-info/WHEEL
tetra-0.8.1.dist-info/top_level.txt
tetra-0.8.1.dist-info/RECORD
