Metadata-Version: 2.4
Name: tetra
Version: 0.8.1
Summary: Full stack component framework for Django using Alpine.js
Author-email: Sam Willis <sam.willis@gmail.com>, Christian González <christian.gonzalez@nerdocs.at>
License-Expression: MIT
Project-URL: Homepage, https://tetraframework.com
Project-URL: Documentation, https://tetra.readthedocs.io
Project-URL: Repository, https://github.com/tetra-framework/tetra
Keywords: python,django,framework,components
Classifier: Development Status :: 3 - Alpha
Classifier: Programming Language :: Python :: 3
Classifier: Framework :: Django
Classifier: Framework :: Django :: 5
Classifier: Operating System :: OS Independent
Classifier: Topic :: Software Development
Requires-Python: >=3.12
License-File: LICENSE
Requires-Dist: cryptography>=37.0.1
Requires-Dist: django>=5.2.3
Requires-Dist: python-dateutil>=2.8.2
Requires-Dist: sourcetypes>=0.0.4
Requires-Dist: pydantic
Dynamic: license-file
